LICENSE
README.md
pyproject.toml
setup.cfg
lega4e_library/__init__.py
lega4e_library/notifier.py
lega4e_library/provider.py
lega4e_library.egg-info/PKG-INFO
lega4e_library.egg-info/SOURCES.txt
lega4e_library.egg-info/dependency_links.txt
lega4e_library.egg-info/requires.txt
lega4e_library.egg-info/top_level.txt
lega4e_library/algorithm/algorithm.py
lega4e_library/algorithm/callback_wrapper.py
lega4e_library/asyncio/async_completer.py
lega4e_library/asyncio/future_queue.py
lega4e_library/asyncio/utils.py
lega4e_library/attrs/jsonkin.py
lega4e_library/attrs/validators.py
lega4e_library/datetime/utils.py
lega4e_library/json/json_manager.py