Metadata-Version: 2.1
Name: lega4e_library
Version: 0.0.7
Summary: Lega4e Library
Author-email: Chersky <lega4e@lega4e.ru>
Maintainer-email: Chersky <lega4e@lega4e.ru>
License: MIT License
Project-URL: Repository, https://github.com/lega4e/python-library.git
Keywords: lega4e
Requires-Python: >=3.9
License-File: LICENSE
Requires-Dist: attrs>=23.2.0
